aiscriptgenerator/Template.yml
aiscriptgenerator/__init__.py
aiscriptgenerator/__main__.py
aiscriptgenerator/alparser.py
aiscriptgenerator/extract_al.py
aiscriptgenerator/server.py
ymlgenerator_mcp-0.0.4.dist-info/METADATA
ymlgenerator_mcp-0.0.4.dist-info/WHEEL
ymlgenerator_mcp-0.0.4.dist-info/entry_points.txt
ymlgenerator_mcp-0.0.4.dist-info/RECORD
