Metadata-Version: 2.4
Name: YMLGenerator-MCP
Version: 0.0.4
Summary: MCP Server for AL Parser - finds pages and fields for Business Central scenarios
Project-URL: Homepage, https://github.com/your-org/aiscriptgenerator
Project-URL: Repository, https://github.com/your-org/aiscriptgenerator
Project-URL: Issues, https://github.com/your-org/aiscriptgenerator/issues
Author: AI Script Generator Team
License-Expression: MIT
Keywords: al,business-central,mcp,parser,yaml
Classifier: Development Status :: 3 - Alpha
Classifier: Intended Audience :: Developers
Classifier: License :: OSI Approved :: MIT License
Classifier: Programming Language :: Python :: 3
Classifier: Programming Language :: Python :: 3.8
Classifier: Programming Language :: Python :: 3.9
Classifier: Programming Language :: Python :: 3.10
Classifier: Programming Language :: Python :: 3.11
Classifier: Programming Language :: Python :: 3.12
Classifier: Programming Language :: Python :: 3.13
Requires-Python: >=3.8
Requires-Dist: fastmcp>=2.11.3
Requires-Dist: mcp[cli]>=1.13.0
Requires-Dist: pyyaml>=6.0
Requires-Dist: rapidfuzz>=3.13.0
Requires-Dist: requests>=2.31.0
Provides-Extra: dev
Requires-Dist: black>=23.0; extra == 'dev'
Requires-Dist: flake8>=6.0; extra == 'dev'
Requires-Dist: mypy>=1.0; extra == 'dev'
Requires-Dist: pytest-cov>=4.0; extra == 'dev'
Requires-Dist: pytest>=7.0; extra == 'dev'
